etiquette/__init__.py
etiquette/_types.py
etiquette/core.py
etiquette/decorum.py
etiquette/py.typed
etiquette-0.0.3.dist-info/METADATA
etiquette-0.0.3.dist-info/WHEEL
etiquette-0.0.3.dist-info/licenses/LICENSE
etiquette-0.0.3.dist-info/RECORD
