Metadata-Version: 2.4
Name: etiquette
Version: 0.0.3
Summary: Semaphored background queue for Asynchronous Server Gateway Interface (ASGI) frameworks
Author-email: Sitt Guruvanich <aekazitt+github@gmail.com>
Maintainer-email: Sitt Guruvanich <aekazitt+github@gmail.com>
License-Expression: MIT
License-File: LICENSE
Keywords: asgi,asynchronous,asyncio,etiquette,extension,fastapi,litestar,plugin,queue,semaphore,starlette,uvloop
Classifier: Environment :: Web Environment
Classifier: Framework :: AsyncIO
Classifier: Framework :: FastAPI
Classifier: Intended Audience :: Developers
Classifier: License :: OSI Approved :: MIT License
Classifier: Operating System :: OS Independent
Classifier: Programming Language :: Python :: 3
Classifier: Programming Language :: Python :: 3 :: Only
Classifier: Programming Language :: Python :: 3.9
Classifier: Programming Language :: Python :: 3.10
Classifier: Programming Language :: Python :: 3.11
Classifier: Programming Language :: Python :: 3.12
Classifier: Programming Language :: Python :: 3.13
Classifier: Programming Language :: Python :: 3.14
Classifier: Topic :: Internet :: WWW/HTTP :: Dynamic Content
Classifier: Topic :: Software Development :: Libraries :: Python Modules
Requires-Python: >=3.9
Provides-Extra: standard
Requires-Dist: uvloop>=0.21.0; extra == 'standard'
